{
    "__comment": [
        "Use ${GITHUBNAME} for your github name",
        "Use ${FULLNAME} for your full name",
        "Use ${REPONAME} for the name of the repository",
        "Use ${YEAR} for the current year",
        "Use ${MONTH} for the current month",
        "Use ${DAY} for the current day of the month"
    ],
    "files": [
        {
            "name": ".gitgitgoc",
            "gitignore": true,
            "oninit": true,
            "description": "A gitgitgo config file",
            "keywords": "gitgitgo,ggg,git",
            "text": [
                "# This is a comment",
                "",
                "# Set the provider",
                "provider=${GITHUBNAME} ",
                "",
                "# Set your full name",
                "fullname=Philipp B.",
                "",
                "# Set your github name",
                "githubname=${GITHUBNAME} "
            ]
        },
        {
            "name": "README.md",
            "gitignore": false,
            "oninit": true,
            "description": "This is a template for a README.md file",
            "text": [
                "<div align=\"center\">",
                "  <br />",
                "  <!-- <img src=\"\" alt=\"${REPONAME}Logo\" width=\"30%\"/> -->",
                "  <h1>${REPONAME}</h1>",
                "  <p>",
                "     Description",
                "  </p>",
                "</div>",
                "",
                "<!-- Badges -->",
                "<div align=\"center\">",
                "   <a href=\"https://github.com/${GITHUBNAME}/${REPONAME}/releases\">",
                "       <img src=\"https://img.shields.io/github/v/release/${GITHUBNAME}/${REPONAME}?display_name=tag\" alt=\"current realease\" />",
                "   </a>",
                "   <a href=\"https://github.com/${GITHUBNAME}/${REPONAME}/blob/master/LICENSE\">",
                "       <img src=\"https://img.shields.io/github/license/${GITHUBNAME}/${REPONAME}\" alt=\"license\" />",
                "   </a>",
                "   <a href=\"https://github.com/${GITHUBNAME}/${REPONAME}/stargazers\">",
                "       <img src=\"https://img.shields.io/github/stars/${GITHUBNAME}/${REPONAME}\" alt=\"stars\" />",
                "   </a>",
                "   <a href=\"https://github.com/${GITHUBNAME}/${REPONAME}/commits/master\">",
                "       <img src=\"https://img.shields.io/github/last-commit/${GITHUBNAME}/${REPONAME}\" alt=\"last commit\" />",
                "   </a>",
                "</div>",
                "",
                "---",
                "",
                "* [Bugs](#bugs)",
                "* [Release Notes](#release-notes)",
                "",
                "---",
                "",
                "## Bugs",
                "",
                "* *no known bugs*",
                "",
                "---",
                "",
                "## [Release Notes](https://github.com/${GITHUBNAME}/${REPONAME}/blob/master/CHANGELOG.md)",
                "",
                "### [v0.0.1](https://github.com/${GITHUBNAME}/${REPONAME}/tree/0.0.1)",
                "",
                "* *Initial release*",
                "",
                "---",
                "",
                "by [${FULLNAME}](https://github.com/${GITHUBNAME})"
            ]
        },
        {
            "name": "CHANGELOG.md",
            "gitignore": false,
            "oninit": true,
            "keywords": "versioning,version",
            "description": "This is a template for a CHANGELOG.md file",
            "text": [
                "# CHANGELOG *${REPONAME}*",
                "",
                "---",
                "",
                "## [v0.0.1](https://github.com/${GITHUBNAME}/${REPONAME}/tree/0.0.1) (${YEAR}-${MONTH}-${DAY})",
                "",
                "* *Initial release*",
                "",
                "---"
            ]
        },
        {
            "name": "ideas.md",
            "gitignore": true,
            "oninit": true,
            "description": "A file to collect ideas for the project",
            "text": ["# IDEAS *${REPONAME}", "- [ ] This is an idea example"]
        },
        {
            "name": ".phil-project",
            "gitignore": false,
            "oninit": true,
            "description": "Initializes a project for the .project-provider",
            "text": [
                "ignore",
                "#logo:assets/logo.png",
                "#logo_small:assets/logo_small.png",
                "#description_translate:de",
                "#version:0.0.1"
            ]
        },
        {
            "name": "src/main.py",
            "gitignore": false,
            "oninit": false,
            "keywords": "python",
            "description": "A main.py file for python projects",
            "text": [
                "def main():",
                "    print(\"Hello World!\")",
                "",
                "",
                "if __name__ == \"__main__\":",
                "    main()"
            ]
        },
        {
            "name": ".prettierrc.json",
            "gitignore": false,
            "oninit": true,
            "keywords": "web,js,typescript,react,angular,vue,prettier",
            "description": "A prettier config file for web projects",
            "text": [
                "{",
                "    \"trailingComma\": \"es5\",",
                "    \"tabWidth\": 4,",
                "    \"semi\": true,",
                "    \"singleQuote\": true",
                "}"
            ]
        },
        {
            "name": "LICENSE",
            "oninit": true,
            "text": [
                "MIT License",
                "",
                "Copyright (c) ${YEAR} ${FULLNAME}",
                "",
                "Permission is hereby granted, free of charge, to any person obtaining a copy",
                "of this software and associated documentation files (the \"Software\"), to deal",
                "in the Software without restriction, including without limitation the rights",
                "to use, copy, modify, merge, publish, distribute, sublicense, and/or sell copies",
                "of the Software, and to permit persons to whom the Software is furnished to do so,",
                "subject to the following conditions:",
                "",
                "The above copyright notice and this permission notice shall be included in all",
                "copies or substantial portions of the Software.",
                "",
                "THE SOFTWARE IS PROVIDED \"AS IS\", WITHOUT WARRANTY OF ANY KIND, EXPRESS OR IMPLIED,",
                "INCLUDING BUT NOT LIMITED TO THE WARRANTIES OF MERCHANTABILITY, FITNESS FOR A",
                "PARTICULAR PURPOSE AND NONINFRINGEMENT. IN NO EVENT SHALL THE AUTHORS OR COPYRIGHT",
                "HOLDERS BE LIABLE FOR ANY CLAIM, DAMAGES OR OTHER LIABILITY, WHETHER IN AN ACTION",
                "OF CONTRACT, TORT OR OTHERWISE, ARISING FROM, OUT OF OR IN CONNECTION WITH THE",
                "SOFTWARE OR THE USE OR OTHER DEALINGS IN THE SOFTWARE."
            ]
        },
        {
            "name": "assets/.gitkeep",
            "gitignore": false,
            "oninit": true,
            "text": []
        },
        {
            "name": ".github/workflows/.gitkeep",
            "gitignore": false,
            "oninit": true,
            "keywords": "ci-cd,actions,pipeline",
            "description": "Initilizes a github actions workflow",
            "text": []
        },
        {
            "name": ".gitattributes",
            "oninit": true,
            "text": ["# git attributes", "# file export-ignore"]
        },
        {
            "name": ".gitignore",
            "oninit": true,
            "text": []
        },
        {
            "name": "MIT-License",
            "text": [
                "MIT License",
                "",
                "Copyright (c) ${YEAR} ${FULLNAME}",
                "",
                "Permission is hereby granted, free of charge, to any person obtaining a copy",
                "of this software and associated documentation files (the \"Software\"), to deal",
                "in the Software without restriction, including without limitation the rights",
                "to use, copy, modify, merge, publish, distribute, sublicense, and/or sell copies",
                "of the Software, and to permit persons to whom the Software is furnished to do so,",
                "subject to the following conditions:",
                "",
                "The above copyright notice and this permission notice shall be included in all",
                "copies or substantial portions of the Software.",
                "",
                "THE SOFTWARE IS PROVIDED \"AS IS\", WITHOUT WARRANTY OF ANY KIND, EXPRESS OR IMPLIED,",
                "INCLUDING BUT NOT LIMITED TO THE WARRANTIES OF MERCHANTABILITY, FITNESS FOR A",
                "PARTICULAR PURPOSE AND NONINFRINGEMENT. IN NO EVENT SHALL THE AUTHORS OR COPYRIGHT",
                "HOLDERS BE LIABLE FOR ANY CLAIM, DAMAGES OR OTHER LIABILITY, WHETHER IN AN ACTION",
                "OF CONTRACT, TORT OR OTHERWISE, ARISING FROM, OUT OF OR IN CONNECTION WITH THE",
                "SOFTWARE OR THE USE OR OTHER DEALINGS IN THE SOFTWARE."
            ]
        },
        {
            "name": "GPL-License",
            "text": [
                "GNU GENERAL PUBLIC LICENSE",
                "Version 3, 29 June 2007",
                "",
                "Copyright (c) ${YEAR} ${FULLNAME}",
                "",
                "This program is free software: you can redistribute it and/or modify",
                "it under the terms of the GNU General Public License as published by",
                "the Free Software Foundation, either version 3 of the License, or",
                "(at your option) any later version.",
                "",
                "This program is distributed in the hope that it will be useful,",
                "but WITHOUT ANY WARRANTY; without even the implied warranty of",
                "MERCHANTABILITY or FITNESS FOR A PARTICULAR PURPOSE. See the",
                "GNU General Public License for more details.",
                "",
                "You should have received a copy of the GNU General Public License",
                "along with this program. If not, see https://www.gnu.org/licenses/."
            ]
        },
        {
            "name": "Apache2.0-License",
            "text": [
                "Apache License",
                "Version 2.0, January 2004",
                "http://www.apache.org/licenses/",
                "",
                "Copyright (c) ${YEAR} ${FULLNAME}",
                "",
                "Licensed under the Apache License, Version 2.0 (the \"License\");",
                "you may not use this file except in compliance with the License.",
                "You may obtain a copy of the License at",
                "",
                "    http://www.apache.org/licenses/LICENSE-2.0",
                "",
                "Unless required by applicable law or agreed to in writing, software",
                "distributed under the License is distributed on an \"AS IS\" BASIS,",
                "WITHOUT WARRANTIES OR CONDITIONS OF ANY KIND, either express or implied.",
                "See the License for the specific language governing permissions and",
                "limitations under the License."
            ]
        },
        {
            "name": "BSD3-License",
            "text": [
                "BSD 3-Clause License",
                "",
                "Copyright (c) ${YEAR} ${FULLNAME}",
                "",
                "Redistribution and use in source and binary forms, with or without modification,",
                "are permitted provided that the following conditions are met:",
                "",
                "1. Redistributions of source code must retain the above copyright notice, this list",
                "   of conditions and the following disclaimer.",
                "",
                "2. Redistributions in binary form must reproduce the above copyright notice, this list",
                "   of conditions and the following disclaimer in the documentation and/or other",
                "   materials provided with the distribution.",
                "",
                "3. Neither the name of the copyright holder nor the names of its contributors may be",
                "   used to endorse or promote products derived from this software without specific",
                "   prior written permission.",
                "",
                "THIS SOFTWARE IS PROVIDED BY THE COPYRIGHT HOLDERS AND CONTRIBUTORS \"AS IS\" AND ANY",
                "EXPRESS OR IMPLIED WARRANTIES, INCLUDING, BUT NOT LIMITED TO, THE IMPLIED WARRANTIES",
                "OF MERCHANTABILITY AND FITNESS FOR A PARTICULAR PURPOSE ARE DISCLAIMED. IN NO EVENT",
                "SHALL THE COPYRIGHT HOLDER OR CONTRIBUTORS BE LIABLE FOR ANY DIRECT, INDIRECT,",
                "INCIDENTAL, SPECIAL, EXEMPLARY, OR CONSEQUENTIAL DAMAGES (INCLUDING, BUT NOT LIMITED",
                "TO, PROCUREMENT OF SUBSTITUTE GOODS OR SERVICES; LOSS OF USE, DATA, OR PROFITS; OR",
                "BUSINESS INTERRUPTION) HOWEVER CAUSED AND ON ANY THEORY OF LIABILITY, WHETHER IN",
                "CONTRACT, STRICT LIABILITY, OR TORT (INCLUDING NEGLIGENCE OR OTHERWISE) ARISING IN",
                "ANY WAY OUT OF THE USE OF THIS SOFTWARE, EVEN IF ADVISED OF THE POSSIBILITY OF",
                "SUCH DAMAGE."
            ]
        },
        {
            "name": "LGPL-License",
            "text": [
                "GNU LESSER GENERAL PUBLIC LICENSE",
                "Version 2.1, February 1999",
                "",
                "Copyright (c) ${YEAR} ${FULLNAME}",
                "",
                "This library is free software; you can redistribute it and/or",
                "modify it under the terms of the GNU Lesser General Public",
                "License as published by the Free Software Foundation; either",
                "version 2.1 of the License, or (at your option) any later version.",
                "",
                "This library is distributed in the hope that it will be useful,",
                "but WITHOUT ANY WARRANTY; without even the implied warranty of",
                "MERCHANTABILITY or FITNESS FOR A PARTICULAR PURPOSE.  See the GNU",
                "Lesser General Public License for more details.",
                "",
                "You should have received a copy of the GNU Lesser General Public",
                "License along with this library; if not, write to the Free Software",
                "Foundation, Inc., 51 Franklin Street, Fifth Floor, Boston, MA 02110-1301 USA"
            ]
        },
        {
            "name": "EPL-License",
            "text": [
                "Eclipse Public License - v 2.0",
                "",
                "Copyright (c) ${YEAR} ${FULLNAME}",
                "",
                "The contents of this file are subject to the Eclipse Public License Version 2.0",
                "(the \"License\"); you may not use this file except in compliance with the License.",
                "You may obtain a copy of the License at http://www.eclipse.org/legal/epl-2.0",
                "",
                "Software distributed under the License is distributed on an \"AS IS\" basis,",
                "WITHOUT WARRANTY OF ANY KIND, either express or implied. See the License for",
                "the specific language governing rights and limitations under the License.",
                "",
                "The Original Software is Eclipse Public License (EPL).",
                "The Initial Developer of the Original Software is IBM Corporation.",
                "",
                "Contributor(s):"
            ]
        },
        {
            "name": "ISC-License",
            "text": [
                "ISC License",
                "",
                "Copyright (c) ${YEAR} ${FULLNAME}",
                "",
                "Permission to use, copy, modify, and/or distribute this software for any purpose",
                "with or without fee is hereby granted, provided that the above copyright notice",
                "and this permission notice appear in all copies.",
                "",
                "THE SOFTWARE IS PROVIDED \"AS IS\" AND THE AUTHOR DISCLAIMS ALL WARRANTIES WITH",
                "REGARD TO THIS SOFTWARE INCLUDING ALL IMPLIED WARRANTIES OF MERCHANTABILITY AND",
                "FITNESS. IN NO EVENT SHALL THE AUTHOR BE LIABLE FOR ANY SPECIAL, DIRECT, INDIRECT,",
                "OR CONSEQUENTIAL DAMAGES OR ANY DAMAGES WHATSOEVER RESULTING FROM LOSS OF USE, DATA",
                "OR PROFITS, WHETHER IN AN ACTION OF CONTRACT, NEGLIGENCE OR OTHER TORTIOUS ACTION,",
                "ARISING OUT OF OR IN CONNECTION WITH THE USE OR PERFORMANCE OF THIS SOFTWARE."
            ]
        }
    ]
}
